investats/__init__.py
investats/__main__.py
investats/cli.py
investats-2.0.0.dist-info/licenses/LICENSE
investats_aggr/__init__.py
investats_aggr/__main__.py
investats_aggr/cli.py
investats_gen/__init__.py
investats_gen/__main__.py
investats_gen/cli.py
investats_scrape/__init__.py
investats_scrape/__main__.py
investats_scrape/cli.py
investats-2.0.0.dist-info/METADATA
investats-2.0.0.dist-info/WHEEL
investats-2.0.0.dist-info/entry_points.txt
investats-2.0.0.dist-info/top_level.txt
investats-2.0.0.dist-info/RECORD
