Metadata-Version: 2.4
Name: investats
Version: 2.0.0
Summary: Investment statistics calculator
Home-page: https://github.com/dmotte/investats
Author: dmotte
License: MIT
Keywords: calculator statistics csv command analysis value analyzer gain yield investment compute return statistic invest investats
Classifier: Intended Audience :: End Users/Desktop
Classifier: Environment :: Console
Classifier: Natural Language :: English
Classifier: License :: OSI Approved :: MIT License
Classifier: Programming Language :: Python
Classifier: Programming Language :: Python :: 3
Classifier: Programming Language :: Python :: 3 :: Only
Classifier: Programming Language :: Python :: 3.12
Classifier: Topic :: Terminals
Classifier: Topic :: Utilities
Requires-Python: >=3.12.3
License-File: LICENSE
Requires-Dist: PyYAML<7,>=6.0.2
Requires-Dist: python-dateutil<2.10,>=2.9.0
Dynamic: license-file
